[{"title":"迷幻的 黑石塔","path":"2026/06/10/悬赏与传闻/迷幻的 黑石塔/","date":"2026-06-10","categories":[],"tags":["传闻"],"description":"","wordcount":0},{"title":"剑湾","path":"2026/06/07/地区概述/剑湾/","date":"2026-06-07","categories":["龙与地下城地区"],"tags":["龙与地下城","地区"],"description":"剑湾是费伦大陆西部沿[剑海]延伸的广阔荒野地带，点缀着众多独立城邦，同时遍布怪物部落。","wordcount":0},{"title":"伪海德拉（False Hydra）数据","path":"2026/06/05/怪物数据/伪海德拉（False Hydra）数据/","date":"2026-06-05","categories":["资料"],"tags":["龙与地下城","怪物"],"description":"这是一头特别的CR12的怪物","wordcount":0},{"title":"西康布Secomber","path":"2026/06/05/地点/西康布/","date":"2026-06-05","categories":["龙与地下城地点"],"tags":["龙与地下城","地点"],"description":"西康布是一座宁静的小镇，它实际上是相对和平的[西部腹地]与更蛮荒的[北方]在[剑湾]沿岸的边境城镇。镇上有许多色彩缤纷的花园。","wordcount":0},{"title":"寂静挽歌 适合5-7级角色的悬疑单次冒险","path":"2026/06/05/寂静挽歌/","date":"2026-06-05","categories":["备团笔记"],"tags":["龙与地下城","备团笔记"],"description":"这是一个为5-7级的玩家准备的，长度6-8小时的短冒险。玩家们将会被雇佣来到一个叫做[西康布]的小镇上，这应该会是一场独特，难忘，甚至有些恐怖的体验。","wordcount":0},{"title":"伪海德拉(False Hydra)","path":"2026/06/04/伪海德拉/","date":"2026-06-04","categories":["资料"],"tags":["龙与地下城","怪物"],"description":"伪海德拉帖子的翻译，这是一种具有奇特机制的怪物，如果你没有遇见过伪海德拉，建议不要阅读本篇内容。","wordcount":0},{"title":"Hello World","path":"2026/05/30/hello-world/","date":"2026-05-30","categories":[],"tags":["Hexo"],"description":"","wordcount":0}]